anilibria_api_client/__init__.py
anilibria_api_client/api_client.py
anilibria_api_client/exceptions.py
anilibria_api_client/helper.py
anilibria_api_client/models.py
anilibria_api_client/types.py
anilibria_api_client/base_api/api_class.py
anilibria_api_client/methods/__init__.py
anilibria_api_client/methods/_helper.py
anilibria_api_client/methods/_libria.py
anilibria_api_client/methods/accounts.py
anilibria_api_client/methods/ads.py
anilibria_api_client/methods/anime.py
anilibria_api_client/methods/app.py
anilibria_api_client/methods/media.py
anilibria_api_client/methods/teams.py
anilibria_api_client-0.2.2.dist-info/licenses/LICENSE
anilibria_api_client-0.2.2.dist-info/METADATA
anilibria_api_client-0.2.2.dist-info/WHEEL
anilibria_api_client-0.2.2.dist-info/top_level.txt
anilibria_api_client-0.2.2.dist-info/RECORD
