Metadata-Version: 2.4
Name: anilibria-api-client
Version: 0.2.2
Summary: Python async API wrapper for AniLibria Swagger
Author-email: semen-bol <syoma.bolotov@bk.ru>
License: MIT
Project-URL: Homepage, https://github.com/semen-bol/Anilibria-Api-Client
Project-URL: Docs, https://anilibria-api-client.readthedocs.io/stable/
Project-URL: Issues, https://github.com/semen-bol/Anilibria-Api-Client/issues
Requires-Python: >=3.13
License-File: LICENSE
Requires-Dist: aiohttp==3.12.15
Requires-Dist: aiofiles==24.1.0
Requires-Dist: pydantic==2.11.7
Requires-Dist: m3u8-To-MP4==0.1.11
Provides-Extra: docs
Requires-Dist: sphinx>=7.0.0; extra == "docs"
Requires-Dist: sphinx-rtd-theme>=1.0.0; extra == "docs"
Requires-Dist: sphinx-autodoc-typehints>=1.0.0; extra == "docs"
Requires-Dist: sphinx_design>=0.6.1; extra == "docs"
Requires-Dist: furo>=2025.7.19; extra == "docs"
Requires-Dist: sphinx-hoverxref>=1.3.0; extra == "docs"
Requires-Dist: readthedocs-sphinx-search>=0.1.2; extra == "docs"
Dynamic: license-file
